{
  "session_info": {
    "start_time": "2025-06-13T15:38:45.442903",
    "export_time": "2025-06-13T15:41:45.826520",
    "total_queries": 2,
    "average_response_time": 2.5915552377700806
  },
  "conversation_history": [
    {
      "query": "hi im mohammed",
      "response": "Hi Mohammed, nice to meet you! How can I help you today?",
      "intent": "chat",
      "confidence": 0.5,
      "agent_used": "Processed by ChatAgent - Intent: chat, Confidence: 0.50",
      "performance_metrics": {
        "start_time": "2025-06-13T15:39:50.399158",
        "processing_steps": [
          {
            "step": "intent_routing",
            "duration": 0.000505,
            "timestamp": "2025-06-13T15:39:50.418911"
          },
          {
            "step": "agent_dispatch_ChatAgent",
            "duration": 1.782218,
            "timestamp": "2025-06-13T15:39:52.201781",
            "agent": "ChatAgent",
            "intent": "chat",
            "confidence": 0.5
          }
        ],
        "total_duration": 1.782723
      },
      "user_context": {
        "current_query": "hi im mohammed",
        "timestamp": "2025-06-13T15:39:50.418793",
        "session_id": "session_66139735",
        "query_length": 14,
        "query_complexity": 0.15,
        "detected_entities": {},
        "intent_confidence": 0.5,
        "conversation_turn": 1,
        "intent_frequency": {
          "chat": 1
        },
        "previous_intents": [],
        "session_duration": 0
      },
      "timestamp": "2025-06-13T15:39:52.201951"
    },
    {
      "query": "what is my name",
      "response": "I do not have access to that information. I am a product recommendation assistant. How can I help you with product recommendations?",
      "intent": "recommend",
      "confidence": 0.65,
      "agent_used": "Processed by RecommendAgent - Intent: recommend, Confidence: 0.65",
      "performance_metrics": {
        "start_time": "2025-06-13T15:39:59.024529",
        "processing_steps": [
          {
            "step": "intent_routing",
            "duration": 0.000139,
            "timestamp": "2025-06-13T15:39:59.025403"
          },
          {
            "step": "agent_dispatch_RecommendAgent",
            "duration": 3.378915,
            "timestamp": "2025-06-13T15:40:02.404623",
            "agent": "RecommendAgent",
            "intent": "recommend",
            "confidence": 0.65
          }
        ],
        "total_duration": 3.379054
      },
      "user_context": {
        "current_query": "what is my name",
        "timestamp": "2025-06-13T15:39:59.025333",
        "session_id": "session_45407383",
        "query_length": 15,
        "query_complexity": 0.2,
        "detected_entities": {},
        "intent_confidence": 0.65,
        "conversation_turn": 1,
        "intent_frequency": {
          "chat": 1,
          "recommend": 1
        },
        "previous_intents": [],
        "session_duration": 0
      },
      "timestamp": "2025-06-13T15:40:02.404780"
    }
  ],
  "session_statistics": {
    "intents_detected": {
      "chat": 1,
      "recommend": 1
    }
  },
  "user_preferences": {
    "show_performance": false,
    "show_intent_detection": true,
    "auto_save_history": true,
    "theme": "default"
  },
  "performance_data": {
    "total_requests": 2,
    "avg_response_time": 2.5808885,
    "max_response_time": 3.379054,
    "intent_distribution": {
      "chat": 1,
      "recommend": 1
    },
    "requests_last_hour": 2
  }
}